drf_kit/__init__.py
drf_kit/cache.py
drf_kit/exceptions.py
drf_kit/fields.py
drf_kit/filters.py
drf_kit/serializers.py
drf_kit/settings.py
drf_kit/signals.py
drf_kit/storage.py
drf_kit/tests.py
drf_kit/managers/__init__.py
drf_kit/managers/availability_managers.py
drf_kit/managers/soft_delete_managers.py
drf_kit/models/__init__.py
drf_kit/models/availability_models.py
drf_kit/models/base_models.py
drf_kit/models/diff_models.py
drf_kit/models/file_models.py
drf_kit/models/inheritance_models.py
drf_kit/models/ordered_models.py
drf_kit/models/soft_delete_models.py
drf_kit/pagination/__init__.py
drf_kit/pagination/custom_pagination.py
drf_kit/pagination/light_pagination.py
drf_kit/views/__init__.py
drf_kit/views/nested_viewsets.py
drf_kit/views/single_nested_viewsets.py
drf_kit/views/stats_views.py
drf_kit/views/viewsets.py
drf_kit-1.49.0.dist-info/METADATA
drf_kit-1.49.0.dist-info/WHEEL
drf_kit-1.49.0.dist-info/RECORD
