Metadata-Version: 2.4
Name: drf-kit
Version: 1.49.0
Summary: DRF Toolkit
Requires-Python: >=3.11
Requires-Dist: django-filter>=24
Requires-Dist: django-ordered-model<3.7.2
Requires-Dist: django>=5.1
Requires-Dist: djangorestframework>=3.15
Requires-Dist: drf-extensions>=0.7
Requires-Dist: psycopg[binary]>=3.2
